[
  {
    "ContainingType": "LoginSRV1.Controllers.AuthController",
    "Method": "Login",
    "RelativePath": "api/Auth/login",
    "HttpMethod": "POST",
    "IsController": true,
    "Order": 0,
    "Parameters": [
      {
        "Name": "usuario",
        "Type": "System.String",
        "IsRequired": false
      },
      {
        "Name": "contrasena",
        "Type": "System.String",
        "IsRequired": false
      },
      {
        "Name": "tipo",
        "Type": "System.String",
        "IsRequired": false
      }
    ],
    "ReturnTypes": []
  },
  {
    "ContainingType": "LoginSRV1.Controllers.AuthController",
    "Method": "Refresh",
    "RelativePath": "api/Auth/refresh",
    "HttpMethod": "POST",
    "IsController": true,
    "Order": 0,
    "Parameters": [
      {
        "Name": "request",
        "Type": "LoginSRV1.Controllers.RefreshTokenRequest",
        "IsRequired": true
      }
    ],
    "ReturnTypes": []
  },
  {
    "ContainingType": "LoginSRV1.Controllers.AuthController",
    "Method": "Validate",
    "RelativePath": "api/Auth/validate",
    "HttpMethod": "GET",
    "IsController": true,
    "Order": 0,
    "Parameters": [
      {
        "Name": "token",
        "Type": "System.String",
        "IsRequired": false
      }
    ],
    "ReturnTypes": []
  },
  {
    "ContainingType": "LoginSRV1.Controllers.WeatherForecastController",
    "Method": "Get",
    "RelativePath": "WeatherForecast",
    "HttpMethod": "GET",
    "IsController": true,
    "Order": 0,
    "Parameters": [],
    "ReturnTypes": [
      {
        "Type": "System.Collections.Generic.IEnumerable\u00601[[LoginSRV1.WeatherForecast, LoginSRV1, Version=1.0.0.0, Culture=neutral, PublicKeyToken=null]]",
        "MediaTypes": [
          "text/plain",
          "application/json",
          "text/json"
        ],
        "StatusCode": 200
      }
    ],
    "EndpointName": "GetWeatherForecast"
  }
]